{
    "評論 1": {
        "內容": "在冷冷的天氣，當作下午的點心、加班晚餐，+半熟蛋+起司實在美味😋，比任何有店面的蔥抓餅厲害👍謝謝老闆賣力的煎炒，謝謝老闆🙏🏻 …",
        "日期": "1 年前"
    },
    "評論 2": {
        "內容": "老闆手腳很快速\n以前也很客氣 …",
        "日期": "11 個月前"
    },
    "評論 3": {
        "內容": "我只能說不要讓我看到，一看到就想買⋯\n服務態度一級棒！！！\n蔥抓餅 絕了⋯\n今天拍照才看到有鐵板麵！ 下次來吃",
        "日期": "1 年前"
    },
    "評論 4": {
        "內容": "新店第一美味蔥抓餅",
        "日期": "2 年前"
    },
    "評論 5": {
        "內容": "老闆頗兇",
        "日期": "11 個月前"
    },
    "評論 6": {
        "內容": "真的好吃",
        "日期": "1 年前"
    }
}